{
	"configurations" : 
	[
		{
			"directories" : 
			[
				{
					"build" : ".",
					"hasInstallRule" : true,
					"jsonFile" : "directory-.-Release-b7051290adf910077341.json",
					"minimumCMakeVersion" : 
					{
						"string" : "3.12"
					},
					"projectIndex" : 0,
					"source" : ".",
					"targetIndexes" : 
					[
						0,
						1,
						2,
						3
					]
				}
			],
			"name" : "Release",
			"projects" : 
			[
				{
					"directoryIndexes" : 
					[
						0
					],
					"name" : "ur_moveit_config",
					"targetIndexes" : 
					[
						0,
						1,
						2,
						3
					]
				}
			],
			"targets" : 
			[
				{
					"directoryIndex" : 0,
					"id" : "ament_cmake_python_build_ur_moveit_config_egg::@6890427a1f51a3e7e1df",
					"jsonFile" : "target-ament_cmake_python_build_ur_moveit_config_egg-Release-f3c3ef9d2e5f7c1268ef.json",
					"name" : "ament_cmake_python_build_ur_moveit_config_egg",
					"projectIndex" : 0
				},
				{
					"directoryIndex" : 0,
					"id" : "ament_cmake_python_copy_ur_moveit_config::@6890427a1f51a3e7e1df",
					"jsonFile" : "target-ament_cmake_python_copy_ur_moveit_config-Release-f16329cab82bcd051d50.json",
					"name" : "ament_cmake_python_copy_ur_moveit_config",
					"projectIndex" : 0
				},
				{
					"directoryIndex" : 0,
					"id" : "uninstall::@6890427a1f51a3e7e1df",
					"jsonFile" : "target-uninstall-Release-0b7a77a3c7914d3e2e3b.json",
					"name" : "uninstall",
					"projectIndex" : 0
				},
				{
					"directoryIndex" : 0,
					"id" : "ur_moveit_config_uninstall::@6890427a1f51a3e7e1df",
					"jsonFile" : "target-ur_moveit_config_uninstall-Release-af1228bf490e4797f2a4.json",
					"name" : "ur_moveit_config_uninstall",
					"projectIndex" : 0
				}
			]
		}
	],
	"kind" : "codemodel",
	"paths" : 
	{
		"build" : "/ws_moveit/build/ur_moveit_config",
		"source" : "/ws_moveit/src/Universal_Robots_ROS2_Driver/ur_moveit_config"
	},
	"version" : 
	{
		"major" : 2,
		"minor" : 3
	}
}
